{
  "errors": [],
  "warnings": [],
  "version": "4.44.2",
  "hash": "a4c973de6b33dc1a620b",
  "publicPath": "/static/",
  "outputPath": "C:\\Users\\Aivars\\Desktop\\Local Sites\\Rounda-node\\build\\static",
  "assetsByChunkName": {
    "rounda-node": [
      "rounda-node.module.js",
      "rounda-node.f4a94589ebaec9a7f76a.hot-update.js"
    ]
  },
  "assets": [
    {
      "name": "f4a94589ebaec9a7f76a.hot-update.json",
      "size": 53,
      "chunks": [],
      "chunkNames": [],
      "info": {
        "hotModuleReplacement": true,
        "immutable": true
      },
      "emitted": false
    },
    {
      "name": "fonts/gangstergrotesk-light.ttf",
      "size": 56340,
      "chunks": [],
      "chunkNames": [],
      "info": {},
      "emitted": false
    },
    {
      "name": "fonts/gangstergrotesk-regular.ttf",
      "size": 55892,
      "chunks": [],
      "chunkNames": [],
      "info": {},
      "emitted": false
    },
    {
      "name": "images/logo.png",
      "size": 28172,
      "chunks": [],
      "chunkNames": [],
      "info": {},
      "emitted": false
    },
    {
      "name": "images/menuIcon.png",
      "size": 281,
      "chunks": [],
      "chunkNames": [],
      "info": {},
      "emitted": false
    },
    {
      "name": "rounda-node.f4a94589ebaec9a7f76a.hot-update.js",
      "size": 17918,
      "chunks": [
        "rounda-node"
      ],
      "chunkNames": [
        "rounda-node"
      ],
      "info": {
        "hotModuleReplacement": true,
        "immutable": true
      },
      "emitted": false
    },
    {
      "name": "rounda-node.module.js",
      "size": 6078433,
      "chunks": [
        "rounda-node"
      ],
      "chunkNames": [
        "rounda-node"
      ],
      "info": {},
      "emitted": false
    }
  ],
  "filteredAssets": 0,
  "entrypoints": {
    "rounda-node": {
      "chunks": [
        "rounda-node"
      ],
      "assets": [
        "rounda-node.module.js",
        "rounda-node.f4a94589ebaec9a7f76a.hot-update.js"
      ],
      "children": {},
      "childAssets": {}
    }
  },
  "namedChunkGroups": {
    "rounda-node": {
      "chunks": [
        "rounda-node"
      ],
      "assets": [
        "rounda-node.module.js",
        "rounda-node.f4a94589ebaec9a7f76a.hot-update.js"
      ],
      "children": {},
      "childAssets": {}
    }
  },
  "logging": {
    "webpack.buildChunkGraph.visitModules": {
      "entries": [],
      "filteredEntries": 2,
      "debug": false
    }
  },
  "children": []
}